oslo_rootwrap/__init__.py
oslo_rootwrap/client.py
oslo_rootwrap/cmd.py
oslo_rootwrap/daemon.py
oslo_rootwrap/filters.py
oslo_rootwrap/jsonrpc.py
oslo_rootwrap/version.py
oslo_rootwrap/wrapper.py
oslo_rootwrap/tests/__init__.py
oslo_rootwrap/tests/run_daemon.py
oslo_rootwrap/tests/test_functional.py
oslo_rootwrap/tests/test_functional_eventlet.py
oslo_rootwrap/tests/test_rootwrap.py
oslo_rootwrap-7.8.0.dist-info/AUTHORS
oslo_rootwrap-7.8.0.dist-info/LICENSE
oslo_rootwrap-7.8.0.dist-info/METADATA
oslo_rootwrap-7.8.0.dist-info/WHEEL
oslo_rootwrap-7.8.0.dist-info/entry_points.txt
oslo_rootwrap-7.8.0.dist-info/pbr.json
oslo_rootwrap-7.8.0.dist-info/top_level.txt
oslo_rootwrap-7.8.0.dist-info/RECORD
